gori/__init__.py
gori/content.py
gori-0.1.dist-info/METADATA
gori-0.1.dist-info/WHEEL
gori-0.1.dist-info/top_level.txt
gori-0.1.dist-info/RECORD
