Metadata-Version: 2.1
Name: gori
Version: 0.1
Summary: This is my first library
Author: Gori Sankar Borah
